{
  "gitSyncId": "67c45521e836f11c3fa21a66_3df969af-0773-44ef-8b84-f269018a9567",
  "unpublishedPage": {
    "isHidden": false,
    "layouts": [
      {
        "dsl": {
          "backgroundColor": "none",
          "bottomRow": 1260,
          "canExtend": true,
          "containerStyle": "none",
          "detachFromLayout": true,
          "dynamicBindingPathList": [],
          "leftColumn": 0,
          "minHeight": 630,
          "parentColumnSpace": 1,
          "parentRowSpace": 1,
          "rightColumn": 1224,
          "snapColumns": 64,
          "snapRows": 61,
          "topRow": 0,
          "type": "CANVAS_WIDGET",
          "version": 92,
          "widgetId": "0",
          "widgetName": "MainContainer"
        }
      }
    ],
    "name": "Statistic",
    "slug": "statistic"
  }
}