{
  "gitSyncId": "67c45521e836f11c3fa21a66_78148b06-256a-4fba-8ade-7bcdd04b9cf8",
  "id": "Fitbook_Admin_Admin_insetslot_6",
  "pluginId": "mongo-plugin",
  "pluginType": "DB",
  "unpublishedAction": {
    "actionConfiguration": {
      "encodeParamsToggle": true,
      "formData": {
        "aggregate": {
          "arrayPipelines": {
            "data": ""
          },
          "limit": {
            "data": "10"
          }
        },
        "collection": {
          "data": "gymbooking"
        },
        "command": {
          "data": "INSERT"
        },
        "count": {
          "query": {
            "data": ""
          }
        },
        "delete": {
          "limit": {
            "data": "SINGLE"
          },
          "query": {
            "data": ""
          }
        },
        "distinct": {
          "key": {
            "data": ""
          },
          "query": {
            "data": ""
          }
        },
        "find": {
          "limit": {
            "data": ""
          },
          "projection": {
            "data": ""
          },
          "query": {
            "data": ""
          },
          "skip": {
            "data": ""
          },
          "sort": {
            "data": ""
          }
        },
        "insert": {
          "documents": {
            "data": "\n{\n\t\"id\": \"\" ,\n  \"time_slot\": {{appsmith.store.multi[6]}}, \n  \"date\": {{DatePicker2.formattedDate}},\n  \"status\": \"available\",\n  \"time_stamp\": \"\"\n}\n"
          }
        },
        "misc": {
          "formToNativeQuery": {
            "data": "{\n  \"insert\": \"gymbooking\",\n  \"documents\": \n{\n\t\"id\": \"\" ,\n  \"time_slot\": {{appsmith.store.multi[6]}}, \n  \"date\": {{DatePicker2.formattedDate}},\n  \"status\": \"available\",\n  \"time_stamp\": \"\"\n}\n\n}\n",
            "status": "SUCCESS"
          }
        },
        "smartSubstitution": {
          "data": true
        },
        "updateMany": {
          "limit": {
            "data": "SINGLE"
          },
          "query": {
            "data": ""
          },
          "update": {
            "data": ""
          }
        }
      },
      "paginationType": "NONE",
      "timeoutInMillisecond": 10000
    },
    "confirmBeforeExecute": false,
    "datasource": {
      "id": "Main",
      "isAutoGenerated": false,
      "name": "Main",
      "pluginId": "mongo-plugin"
    },
    "dynamicBindingPathList": [
      {
        "key": "formData.insert.documents.data"
      }
    ],
    "executeOnLoad": false,
    "name": "Admin_insetslot_6",
    "pageId": "Fitbook_Admin",
    "userSetOnLoad": false
  }
}