{
  "gitSyncId": "67c45521e836f11c3fa21a66_5992f826-9a9d-4941-852c-ce41c099f331",
  "id": "Bill_Admin_get_bill",
  "pluginId": "mongo-plugin",
  "pluginType": "DB",
  "unpublishedAction": {
    "actionConfiguration": {
      "encodeParamsToggle": true,
      "formData": {
        "aggregate": {
          "arrayPipelines": {
            "data": "{}"
          },
          "limit": {
            "data": "10"
          }
        },
        "collection": {
          "data": "payment"
        },
        "command": {
          "data": "FIND"
        },
        "count": {
          "query": {
            "data": ""
          }
        },
        "delete": {
          "limit": {
            "data": "SINGLE"
          },
          "query": {
            "data": ""
          }
        },
        "distinct": {
          "key": {
            "data": ""
          },
          "query": {
            "data": ""
          }
        },
        "find": {
          "limit": {
            "data": ""
          },
          "projection": {
            "data": ""
          },
          "query": {
            "data": "{}"
          },
          "skip": {
            "data": ""
          },
          "sort": {
            "data": "{date :-1}"
          }
        },
        "insert": {
          "documents": {
            "data": ""
          }
        },
        "misc": {
          "formToNativeQuery": {
            "data": "{\n  \"find\": \"payment\",\n  \"filter\": {},\n  \"sort\": {date :-1},\n  \"limit\": 10,\n  \"batchSize\": 10\n}\n",
            "status": "SUCCESS"
          }
        },
        "smartSubstitution": {
          "data": true
        },
        "updateMany": {
          "limit": {
            "data": "SINGLE"
          },
          "query": {
            "data": ""
          },
          "update": {
            "data": ""
          }
        }
      },
      "paginationType": "NONE",
      "timeoutInMillisecond": 10000
    },
    "confirmBeforeExecute": false,
    "datasource": {
      "id": "Main",
      "isAutoGenerated": false,
      "name": "Main",
      "pluginId": "mongo-plugin"
    },
    "dynamicBindingPathList": [],
    "executeOnLoad": true,
    "name": "get_bill",
    "pageId": "Bill_Admin",
    "userSetOnLoad": false
  }
}