{
  "gitSyncId": "67c45521e836f11c3fa21a66_1113d21c-27c6-4d2d-a72c-5ec404f3cd6f",
  "id": "Poolbook_Admin_submit.SubmitonClick",
  "pluginId": "js-plugin",
  "pluginType": "JS",
  "unpublishedAction": {
    "actionConfiguration": {
      "encodeParamsToggle": true,
      "jsArguments": [],
      "paginationType": "NONE",
      "timeoutInMillisecond": 10000
    },
    "collectionId": "Poolbook_Admin_submit",
    "confirmBeforeExecute": false,
    "datasource": {
      "isAutoGenerated": false,
      "name": "UNUSED_DATASOURCE",
      "pluginId": "js-plugin"
    },
    "dynamicBindingPathList": [
      {
        "key": "body"
      }
    ],
    "executeOnLoad": false,
    "fullyQualifiedName": "submit.SubmitonClick",
    "name": "SubmitonClick",
    "pageId": "Poolbook_Admin",
    "userSetOnLoad": false
  }
}