{
  "gitSyncId": "67c45521e836f11c3fa21a66_dd6a1a56-f80c-4018-b543-c9a54ce41d8f",
  "id": "Bill_Admin_insert_bill",
  "pluginId": "mongo-plugin",
  "pluginType": "DB",
  "unpublishedAction": {
    "actionConfiguration": {
      "encodeParamsToggle": true,
      "formData": {
        "aggregate": {
          "arrayPipelines": {
            "data": ""
          },
          "limit": {
            "data": "10"
          }
        },
        "collection": {
          "data": "payment"
        },
        "command": {
          "data": "INSERT"
        },
        "count": {
          "query": {
            "data": ""
          }
        },
        "delete": {
          "limit": {
            "data": "SINGLE"
          },
          "query": {
            "data": ""
          }
        },
        "distinct": {
          "key": {
            "data": ""
          },
          "query": {
            "data": ""
          }
        },
        "find": {
          "limit": {
            "data": ""
          },
          "projection": {
            "data": ""
          },
          "query": {
            "data": ""
          },
          "skip": {
            "data": ""
          },
          "sort": {
            "data": ""
          }
        },
        "insert": {
          "documents": {
            "data": "{ \n  \"id\": \"{{room.selectedOptionValue}}\",\n\t\"electricity\" : \"{{elec.text}}\",\n\t\"water\" : \"{{water.text}}\",\n\t\"rent\" : \"{{Select1.selectedOptionValue}}\",\n  \"date\": \"{{bookdate1.formattedDate}}\",\n\t\"status\" : \"Unpaid\"\n}\n"
          }
        },
        "misc": {
          "formToNativeQuery": {
            "data": "{\n  \"insert\": \"payment\",\n  \"documents\": { \n  \"id\": \"{{room.selectedOptionValue}}\",\n\t\"electricity\" : \"{{elec.text}}\",\n\t\"water\" : \"{{water.text}}\",\n\t\"rent\" : \"{{Select1.selectedOptionValue}}\",\n  \"date\": \"{{bookdate1.formattedDate}}\",\n\t\"status\" : \"Unpaid\"\n}\n\n}\n",
            "status": "SUCCESS"
          }
        },
        "smartSubstitution": {
          "data": true
        },
        "updateMany": {
          "limit": {
            "data": "SINGLE"
          },
          "query": {
            "data": ""
          },
          "update": {
            "data": ""
          }
        }
      },
      "paginationType": "NONE",
      "timeoutInMillisecond": 10000
    },
    "confirmBeforeExecute": false,
    "datasource": {
      "id": "Main",
      "isAutoGenerated": false,
      "name": "Main",
      "pluginId": "mongo-plugin"
    },
    "dynamicBindingPathList": [
      {
        "key": "formData.insert.documents.data"
      }
    ],
    "executeOnLoad": false,
    "name": "insert_bill",
    "pageId": "Bill_Admin",
    "userSetOnLoad": false
  }
}