{
  "gitSyncId": "67c45521e836f11c3fa21a66_1f810628-a013-4701-ada9-5ff9b1e4c911",
  "id": "ContactAdmin_Total_record_admin1",
  "pluginId": "mongo-plugin",
  "pluginType": "DB",
  "unpublishedAction": {
    "actionConfiguration": {
      "encodeParamsToggle": true,
      "formData": {
        "aggregate": {
          "limit": {
            "data": "10"
          }
        },
        "collection": {
          "data": "admin"
        },
        "command": {
          "data": "COUNT"
        },
        "count": {
          "query": {
            "data": "{{{ name: {$regex: Table1.searchText} }}}"
          }
        },
        "delete": {
          "limit": {
            "data": "SINGLE"
          }
        },
        "misc": {
          "formToNativeQuery": {
            "data": "{\n  \"count\": \"admin\",\n  \"query\": {{{ name: {$regex: Table1.searchText} }}},\n}\n",
            "status": "SUCCESS"
          }
        },
        "smartSubstitution": {
          "data": true
        },
        "updateMany": {
          "limit": {
            "data": "SINGLE"
          }
        }
      },
      "paginationType": "NONE",
      "timeoutInMillisecond": 10000
    },
    "confirmBeforeExecute": false,
    "datasource": {
      "id": "Main",
      "isAutoGenerated": false,
      "name": "Main",
      "pluginId": "mongo-plugin"
    },
    "dynamicBindingPathList": [
      {
        "key": "formData.count.query.data"
      }
    ],
    "executeOnLoad": false,
    "name": "Total_record_admin1",
    "pageId": "ContactAdmin",
    "userSetOnLoad": false
  }
}